{
    "songList": [
        {
            "artist": "Young Thug",
            "title": "Just How It Is",
            "album": "So Much Fun",
            "year": "2019",
            "fetched": false
        },
        {
            "artist": "Young Thug",
            "title": "Sup Mate",
            "album": "So Much Fun",
            "year": "2019",
            "fetched": false
        },
        {
            "artist": "Young Thug",
            "title": "Ecstasy",
            "album": "So Much Fun",
            "year": "2019",
            "fetched": false
        },
        {
            "artist": "Young Thug",
            "title": "Hot",
            "album": "So Much Fun",
            "year": "2019",
            "fetched": false
        },
        {
            "artist": "Young Thug",
            "title": "Light It Up",
            "album": "So Much Fun",
            "year": "2019",
            "fetched": false
        },
        {
            "artist": "Young Thug",
            "title": "Surf",
            "album": "So Much Fun",
            "year": "2019",
            "fetched": false
        },
        {
            "artist": "Young Thug",
            "title": "Bad Bad Bad",
            "album": "So Much Fun",
            "year": "2019",
            "fetched": false
        },
        {
            "artist": "Young Thug",
            "title": "Lil Baby",
            "album": "So Much Fun",
            "year": "2019",
            "fetched": false
        },
        {
            "artist": "Young Thug",
            "title": "What's The Move?",
            "album": "So Much Fun",
            "year": "2019",
            "fetched": false
        },
        {
            "artist": "Young Thug",
            "title": "I Bought Her",
            "album": "So Much Fun",
            "year": "2019",
            "fetched": false
        },
        {
            "artist": "Young Thug",
            "title": "Jumped Out the Window",
            "album": "So Much Fun",
            "year": "2019",
            "fetched": false
        },
        {
            "artist": "Young Thug",
            "title": "I'm Scared",
            "album": "So Much Fun",
            "year": "2019",
            "fetched": false
        },
        {
            "artist": "Young Thug",
            "title": "Cartier Gucci Scarf",
            "album": "So Much Fun",
            "year": "2019",
            "fetched": false
        },
        {
            "artist": "Young Thug",
            "title": "Big Tipper",
            "album": "So Much Fun",
            "year": "2019",
            "fetched": false
        },
        {
            "artist": "Young Thug",
            "title": "Pussy",
            "album": "So Much Fun",
            "year": "2019",
            "fetched": false
        },
        {
            "artist": "Young Thug",
            "title": "Circle of Bosses",
            "album": "So Much Fun",
            "year": "2019",
            "fetched": false
        },
        {
            "artist": "Young Thug",
            "title": "Mannequin Challenge",
            "album": "So Much Fun",
            "year": "2019",
            "fetched": false
        },
        {
            "artist": "Young Thug",
            "title": "Boy Back",
            "album": "So Much Fun",
            "year": "2019",
            "fetched": false
        },
        {
            "artist": "Young Thug",
            "title": "The London",
            "album": "So Much Fun",
            "year": "2019",
            "fetched": false
        },
        {
            "artist": "Young Thug",
            "title": "Diamonds",
            "album": "So Much Fun",
            "year": "2019",
            "fetched": false
        },
        {
            "artist": "Young Thug",
            "title": "Hop Off A Jet",
            "album": "So Much Fun",
            "year": "2019",
            "fetched": false
        },
        {
            "artist": "Young Thug",
            "title": "Die Today",
            "album": "So Much Fun",
            "year": "2019",
            "fetched": false
        },
        {
            "artist": "Young Thug",
            "title": "Millions",
            "album": "So Much Fun",
            "year": "2019",
            "fetched": false
        },
        {
            "artist": "Young Thug",
            "title": "Hot (Remix)",
            "album": "So Much Fun",
            "year": "2019",
            "fetched": false
        }
    ]
}